{
  "updatedAt": "21-10-2025, 00:03:43 am",
  "items": [
    {
      "symbol": "^spx",
      "name": "S&P 500",
      "price": 6739.51,
      "change": 75.5,
      "changePercent": 1.1329514811652444
    },
    {
      "symbol": "^ndx",
      "name": "NASDAQ 100",
      "price": 25164.13,
      "change": 346.1800000000003,
      "changePercent": 1.3948774979400003
    },
    {
      "symbol": "^hsi",
      "name": "Hang Seng",
      "price": 25858.83,
      "change": 611.7300000000032,
      "changePercent": 2.422971351165097
    },
    {
      "symbol": "^shc",
      "name": "Shanghai Comp.",
      "price": 3863.8926,
      "change": 24.137300000000323,
      "changePercent": 0.6286155787062869
    }
  ]
}