{
  "updatedAt": "08-01-2026, 09:12:56 pm",
  "items": [
    {
      "symbol": "^spx",
      "name": "S&P 500",
      "price": 6923.59,
      "change": 2.6599999999998545,
      "changePercent": 0.03843414107641392
    },
    {
      "symbol": "^ndx",
      "name": "NASDAQ 100",
      "price": 25498.443,
      "change": -155.45700000000215,
      "changePercent": -0.6059780384269142
    },
    {
      "symbol": "^hsi",
      "name": "Hang Seng",
      "price": 26149.31,
      "change": -309.6399999999994,
      "changePercent": -1.1702656379032403
    },
    {
      "symbol": "^shc",
      "name": "Shanghai Comp.",
      "price": 4082.9788,
      "change": -2.793500000000222,
      "changePercent": -0.06837140679621871
    }
  ]
}