{
  "updatedAt": "14-10-2025, 07:23:13 pm",
  "items": [
    {
      "symbol": "^spx",
      "name": "S&P 500",
      "price": 6574.4,
      "change": -80.32000000000062,
      "changePercent": -1.206962877476447
    },
    {
      "symbol": "^ndx",
      "name": "NASDAQ 100",
      "price": 24337.025,
      "change": -413.22499999999854,
      "changePercent": -1.669579095160649
    },
    {
      "symbol": "^hsi",
      "name": "Hang Seng",
      "price": 25441.35,
      "change": -448.130000000001,
      "changePercent": -1.73093472715559
    },
    {
      "symbol": "^shc",
      "name": "Shanghai Comp.",
      "price": 3865.2289,
      "change": -24.273299999999836,
      "changePercent": -0.624072149901338
    }
  ]
}