{
  "updatedAt": "06-11-2025, 00:27:25 pm",
  "items": [
    {
      "symbol": "^spx",
      "name": "S&P 500",
      "price": 6796.29,
      "change": 24.73999999999978,
      "changePercent": 0.36535209811638075
    },
    {
      "symbol": "^ndx",
      "name": "NASDAQ 100",
      "price": 25620.03,
      "change": 184.3299999999981,
      "changePercent": 0.7246901009211387
    },
    {
      "symbol": "^hsi",
      "name": "Hang Seng",
      "price": 26408.41,
      "change": 473,
      "changePercent": 1.823761413449797
    },
    {
      "symbol": "^shc",
      "name": "Shanghai Comp.",
      "price": 4006.3096,
      "change": 37.06129999999985,
      "changePercent": 0.9337107985912557
    }
  ]
}