{
  "updatedAt": "26-09-2025, 07:50:35 pm",
  "items": [
    {
      "symbol": "^spx",
      "name": "S&P 500",
      "price": 6621.47,
      "change": 16.75,
      "changePercent": 0.2536065117067794
    },
    {
      "symbol": "^ndx",
      "name": "NASDAQ 100",
      "price": 24378.545,
      "change": -18.765000000003056,
      "changePercent": -0.07691421718215269
    },
    {
      "symbol": "^hsi",
      "name": "Hang Seng",
      "price": 26128.2,
      "change": -356.47999999999956,
      "changePercent": -1.345985679268164
    },
    {
      "symbol": "^shc",
      "name": "Shanghai Comp.",
      "price": 3828.106,
      "change": -25.19609999999966,
      "changePercent": -0.6538833277567223
    }
  ]
}