{
  "updatedAt": "27-11-2025, 05:22:01 am",
  "items": [
    {
      "symbol": "^spx",
      "name": "S&P 500",
      "price": 6812.61,
      "change": 46.72999999999956,
      "changePercent": 0.6906714278113055
    },
    {
      "symbol": "^ndx",
      "name": "NASDAQ 100",
      "price": 25236.94,
      "change": 218.5799999999981,
      "changePercent": 0.8736783706046204
    },
    {
      "symbol": "^hsi",
      "name": "Hang Seng",
      "price": 25928.08,
      "change": 33.530000000002474,
      "changePercent": 0.12948670666222226
    },
    {
      "symbol": "^shc",
      "name": "Shanghai Comp.",
      "price": 3864.1844,
      "change": -5.838400000000092,
      "changePercent": -0.1508621602952854
    }
  ]
}