{
  "updatedAt": "19-09-2025, 00:59:30 pm",
  "items": [
    {
      "symbol": "^spx",
      "name": "S&P 500",
      "price": 6631.96,
      "change": 31.609999999999673,
      "changePercent": 0.4789139969850034
    },
    {
      "symbol": "^ndx",
      "name": "NASDAQ 100",
      "price": 24454.89,
      "change": 231.20000000000073,
      "changePercent": 0.9544375774293709
    },
    {
      "symbol": "^hsi",
      "name": "Hang Seng",
      "price": 26492.08,
      "change": -52.7699999999968,
      "changePercent": -0.1987956232564765
    },
    {
      "symbol": "^shc",
      "name": "Shanghai Comp.",
      "price": 3820.0894,
      "change": -11.566800000000057,
      "changePercent": -0.30187468280687757
    }
  ]
}