{
  "updatedAt": "17-09-2025, 00:53:52 am",
  "items": [
    {
      "symbol": "^spx",
      "name": "S&P 500",
      "price": 6613.79,
      "change": -1.4899999999997817,
      "changePercent": -0.02252361200130277
    },
    {
      "symbol": "^ndx",
      "name": "NASDAQ 100",
      "price": 24298.445,
      "change": 4.665000000000873,
      "changePercent": 0.019202446058212735
    },
    {
      "symbol": "^hsi",
      "name": "Hang Seng",
      "price": 26438.51,
      "change": -8.05000000000291,
      "changePercent": -0.030438741371289536
    },
    {
      "symbol": "^shc",
      "name": "Shanghai Comp.",
      "price": 3861.8651,
      "change": 1.3614999999999782,
      "changePercent": 0.035267419514904176
    }
  ]
}