{
  "updatedAt": "13-02-2026, 10:36:52 pm",
  "items": [
    {
      "symbol": "^spx",
      "name": "S&P 500",
      "price": 6874.36,
      "change": 41.599999999999454,
      "changePercent": 0.6088315702585697
    },
    {
      "symbol": "^ndx",
      "name": "NASDAQ 100",
      "price": 24852.996,
      "change": 165.3859999999986,
      "changePercent": 0.6699149897458628
    },
    {
      "symbol": "^hsi",
      "name": "Hang Seng",
      "price": 26567.12,
      "change": -465.4200000000019,
      "changePercent": -1.7217028070614224
    },
    {
      "symbol": "^shc",
      "name": "Shanghai Comp.",
      "price": 4082.0726,
      "change": -51.94519999999966,
      "changePercent": -1.2565306322580339
    }
  ]
}