{
  "updatedAt": "28-10-2025, 01:22:20 am",
  "items": [
    {
      "symbol": "^spx",
      "name": "S&P 500",
      "price": 6875.23,
      "change": 83.53999999999996,
      "changePercent": 1.2300325839371344
    },
    {
      "symbol": "^ndx",
      "name": "NASDAQ 100",
      "price": 25822.658,
      "change": 464.4979999999996,
      "changePercent": 1.8317496222123357
    },
    {
      "symbol": "^hsi",
      "name": "Hang Seng",
      "price": 26433.7,
      "change": 273.5499999999993,
      "changePercent": 1.045674432294919
    },
    {
      "symbol": "^shc",
      "name": "Shanghai Comp.",
      "price": 3996.9445,
      "change": 46.633000000000266,
      "changePercent": 1.1804891842073788
    }
  ]
}