{
  "updatedAt": "05-12-2025, 10:27:59 pm",
  "items": [
    {
      "symbol": "^spx",
      "name": "S&P 500",
      "price": 6875.92,
      "change": 18.800000000000182,
      "changePercent": 0.2741675805586045
    },
    {
      "symbol": "^ndx",
      "name": "NASDAQ 100",
      "price": 25709.299,
      "change": 127.59899999999834,
      "changePercent": 0.49879015077183436
    },
    {
      "symbol": "^hsi",
      "name": "Hang Seng",
      "price": 26085.08,
      "change": 149.1800000000003,
      "changePercent": 0.575187288661663
    },
    {
      "symbol": "^shc",
      "name": "Shanghai Comp.",
      "price": 3902.8076,
      "change": 27.014300000000276,
      "changePercent": 0.6970005340584152
    }
  ]
}