{
  "updatedAt": "12-09-2025, 00:18:35 pm",
  "items": [
    {
      "symbol": "^spx",
      "name": "S&P 500",
      "price": 6587.47,
      "change": 55.43000000000029,
      "changePercent": 0.8485863528086217
    },
    {
      "symbol": "^ndx",
      "name": "NASDAQ 100",
      "price": 23992.56,
      "change": 143.29000000000087,
      "changePercent": 0.600815035428761
    },
    {
      "symbol": "^hsi",
      "name": "Hang Seng",
      "price": 26388.34,
      "change": 302.02000000000044,
      "changePercent": 1.1577715829599593
    },
    {
      "symbol": "^shc",
      "name": "Shanghai Comp.",
      "price": 3870.8069,
      "change": -4.502500000000055,
      "changePercent": -0.11618427163519007
    }
  ]
}