{
  "updatedAt": "03-09-2025, 01:22:19 am",
  "items": [
    {
      "symbol": "^spx",
      "name": "S&P 500",
      "price": 6411.88,
      "change": -48.38000000000011,
      "changePercent": -0.7488862677353559
    },
    {
      "symbol": "^ndx",
      "name": "NASDAQ 100",
      "price": 23222.371,
      "change": -193.04899999999907,
      "changePercent": -0.8244524334818639
    },
    {
      "symbol": "^hsi",
      "name": "Hang Seng",
      "price": 25496.55,
      "change": -120.86999999999898,
      "changePercent": -0.47182737371678724
    },
    {
      "symbol": "^shc",
      "name": "Shanghai Comp.",
      "price": 3858.1334,
      "change": -17.396999999999935,
      "changePercent": -0.44889339534015615
    }
  ]
}