{
  "updatedAt": "30-09-2025, 07:51:19 pm",
  "items": [
    {
      "symbol": "^spx",
      "name": "S&P 500",
      "price": 6656.44,
      "change": -4.770000000000437,
      "changePercent": -0.07160861164864096
    },
    {
      "symbol": "^ndx",
      "name": "NASDAQ 100",
      "price": 24558.813,
      "change": -52.53700000000026,
      "changePercent": -0.21346655100187625
    },
    {
      "symbol": "^hsi",
      "name": "Hang Seng",
      "price": 26855.56,
      "change": 232.6800000000003,
      "changePercent": 0.8739850835071198
    },
    {
      "symbol": "^shc",
      "name": "Shanghai Comp.",
      "price": 3882.7774,
      "change": 20.245699999999943,
      "changePercent": 0.5241562159865236
    }
  ]
}