{
  "updatedAt": "03-12-2025, 01:01:34 am",
  "items": [
    {
      "symbol": "^spx",
      "name": "S&P 500",
      "price": 6829.91,
      "change": 17.279999999999745,
      "changePercent": 0.25364653591931086
    },
    {
      "symbol": "^ndx",
      "name": "NASDAQ 100",
      "price": 25548.266,
      "change": 205.41600000000108,
      "changePercent": 0.8105481427700558
    },
    {
      "symbol": "^hsi",
      "name": "Hang Seng",
      "price": 26095.05,
      "change": 61.79000000000087,
      "changePercent": 0.23735022044876777
    },
    {
      "symbol": "^shc",
      "name": "Shanghai Comp.",
      "price": 3897.7116,
      "change": -16.29449999999997,
      "changePercent": -0.41631258571620444
    }
  ]
}