{
  "updatedAt": "19-12-2025, 00:30:45 am",
  "items": [
    {
      "symbol": "^spx",
      "name": "S&P 500",
      "price": 6791.42,
      "change": 69.98999999999978,
      "changePercent": 1.0412962717754968
    },
    {
      "symbol": "^ndx",
      "name": "NASDAQ 100",
      "price": 25093.49,
      "change": 445.880000000001,
      "changePercent": 1.8090192111933003
    },
    {
      "symbol": "^hsi",
      "name": "Hang Seng",
      "price": 25498.13,
      "change": 29.350000000002183,
      "changePercent": 0.11523912806189454
    },
    {
      "symbol": "^shc",
      "name": "Shanghai Comp.",
      "price": 3876.3705,
      "change": 6.092999999999847,
      "changePercent": 0.15743057183883705
    }
  ]
}