{
  "updatedAt": "05-12-2025, 11:16:23 am",
  "items": [
    {
      "symbol": "^spx",
      "name": "S&P 500",
      "price": 6857.12,
      "change": 7.399999999999636,
      "changePercent": 0.108033613052791
    },
    {
      "symbol": "^ndx",
      "name": "NASDAQ 100",
      "price": 25581.7,
      "change": -24.840000000000146,
      "changePercent": -0.09700646787890962
    },
    {
      "symbol": "^hsi",
      "name": "Hang Seng",
      "price": 25986.18,
      "change": 50.279999999998836,
      "changePercent": 0.1938625611603948
    },
    {
      "symbol": "^shc",
      "name": "Shanghai Comp.",
      "price": 3895.3799,
      "change": 19.58660000000009,
      "changePercent": 0.5053571871337951
    }
  ]
}