{
  "updatedAt": "17-09-2025, 04:21:55 pm",
  "items": [
    {
      "symbol": "^spx",
      "name": "S&P 500",
      "price": 6606.76,
      "change": -8.519999999999527,
      "changePercent": -0.12879273439672284
    },
    {
      "symbol": "^ndx",
      "name": "NASDAQ 100",
      "price": 24274.25,
      "change": -19.529999999998836,
      "changePercent": -0.08039094780638845
    },
    {
      "symbol": "^hsi",
      "name": "Hang Seng",
      "price": 26908.39,
      "change": 469.880000000001,
      "changePercent": 1.7772559800079544
    },
    {
      "symbol": "^shc",
      "name": "Shanghai Comp.",
      "price": 3876.3409,
      "change": 14.475800000000163,
      "changePercent": 0.37483960793970156
    }
  ]
}