{
  "updatedAt": "16-12-2025, 01:01:44 am",
  "items": [
    {
      "symbol": "^spx",
      "name": "S&P 500",
      "price": 6816.86,
      "change": -10.550000000000182,
      "changePercent": -0.15452418999298684
    },
    {
      "symbol": "^ndx",
      "name": "NASDAQ 100",
      "price": 25109.621,
      "change": -87.10900000000038,
      "changePercent": -0.345715495621854
    },
    {
      "symbol": "^hsi",
      "name": "Hang Seng",
      "price": 25628.88,
      "change": -347.90999999999985,
      "changePercent": -1.3393109772223581
    },
    {
      "symbol": "^shc",
      "name": "Shanghai Comp.",
      "price": 3867.9209,
      "change": -21.424799999999777,
      "changePercent": -0.5508587215582246
    }
  ]
}