{
  "updatedAt": "05-03-2026, 01:28:12 am",
  "items": [
    {
      "symbol": "^spx",
      "name": "S&P 500",
      "price": 6882.59,
      "change": 65.96000000000004,
      "changePercent": 0.9676335667331223
    },
    {
      "symbol": "^ndx",
      "name": "NASDAQ 100",
      "price": 25152.455,
      "change": 432.375,
      "changePercent": 1.749084145358753
    },
    {
      "symbol": "^hsi",
      "name": "Hang Seng",
      "price": 25249.48,
      "change": -518.6000000000022,
      "changePercent": -2.012567486595828
    },
    {
      "symbol": "^shc",
      "name": "Shanghai Comp.",
      "price": 4082.474,
      "change": -40.202000000000226,
      "changePercent": -0.9751433292356766
    }
  ]
}