{
  "updatedAt": "28-10-2025, 09:27:13 pm",
  "items": [
    {
      "symbol": "^spx",
      "name": "S&P 500",
      "price": 6877.04,
      "change": 1.8800000000001091,
      "changePercent": 0.027344818156960844
    },
    {
      "symbol": "^ndx",
      "name": "NASDAQ 100",
      "price": 25910.24,
      "change": 88.70000000000073,
      "changePercent": 0.3435116573217582
    },
    {
      "symbol": "^hsi",
      "name": "Hang Seng",
      "price": 26346.14,
      "change": -87.56000000000131,
      "changePercent": -0.33124382890023457
    },
    {
      "symbol": "^shc",
      "name": "Shanghai Comp.",
      "price": 3988.2239,
      "change": -8.720600000000104,
      "changePercent": -0.2181816635182226
    }
  ]
}