{
  "updatedAt": "09-10-2025, 09:23:53 am",
  "items": [
    {
      "symbol": "^spx",
      "name": "S&P 500",
      "price": 6753.72,
      "change": 39.13000000000011,
      "changePercent": 0.582760823817986
    },
    {
      "symbol": "^ndx",
      "name": "NASDAQ 100",
      "price": 25136.62,
      "change": 296.3899999999994,
      "changePercent": 1.1931854093138405
    },
    {
      "symbol": "^hsi",
      "name": "Hang Seng",
      "price": 26821.8,
      "change": -7.6599999999998545,
      "changePercent": -0.028550705083143134
    },
    {
      "symbol": "^shc",
      "name": "Shanghai Comp.",
      "price": 3931.0718,
      "change": 48.29440000000022,
      "changePercent": 1.2438106804680646
    }
  ]
}