{
  "updatedAt": "28-01-2026, 02:20:01 am",
  "items": [
    {
      "symbol": "^spx",
      "name": "S&P 500",
      "price": 6982.41,
      "change": 32.18000000000029,
      "changePercent": 0.463006260224486
    },
    {
      "symbol": "^ndx",
      "name": "NASDAQ 100",
      "price": 25957.541,
      "change": 244.33100000000195,
      "changePercent": 0.9502158618080044
    },
    {
      "symbol": "^hsi",
      "name": "Hang Seng",
      "price": 27126.95,
      "change": 361.4300000000003,
      "changePercent": 1.350356727610748
    },
    {
      "symbol": "^shc",
      "name": "Shanghai Comp.",
      "price": 4139.9041,
      "change": 7.298899999999776,
      "changePercent": 0.17661740347226432
    }
  ]
}