{
  "updatedAt": "24-10-2025, 00:49:08 am",
  "items": [
    {
      "symbol": "^spx",
      "name": "S&P 500",
      "price": 6747.33,
      "change": 47.93000000000029,
      "changePercent": 0.715437203331646
    },
    {
      "symbol": "^ndx",
      "name": "NASDAQ 100",
      "price": 25115.002,
      "change": 235.992000000002,
      "changePercent": 0.9485586444155215
    },
    {
      "symbol": "^hsi",
      "name": "Hang Seng",
      "price": 25967.98,
      "change": 186.20999999999913,
      "changePercent": 0.7222545232542185
    },
    {
      "symbol": "^shc",
      "name": "Shanghai Comp.",
      "price": 3922.4101,
      "change": 8.652500000000146,
      "changePercent": 0.22107909800035
    }
  ]
}