{
  "updatedAt": "19-02-2026, 01:32:52 am",
  "items": [
    {
      "symbol": "^spx",
      "name": "S&P 500",
      "price": 6870.92,
      "change": 27.699999999999818,
      "changePercent": 0.4047802058095431
    },
    {
      "symbol": "^ndx",
      "name": "NASDAQ 100",
      "price": 24853.139,
      "change": 151.53900000000067,
      "changePercent": 0.6134784791268609
    },
    {
      "symbol": "^hsi",
      "name": "Hang Seng",
      "price": 26705.94,
      "change": 138.8199999999997,
      "changePercent": 0.5225255880200779
    },
    {
      "symbol": "^shc",
      "name": "Shanghai Comp.",
      "price": 4082.0726,
      "change": -51.94519999999966,
      "changePercent": -1.2565306322580339
    }
  ]
}