{
  "updatedAt": "31-10-2025, 11:24:49 am",
  "items": [
    {
      "symbol": "^spx",
      "name": "S&P 500",
      "price": 6822.34,
      "change": -68.25,
      "changePercent": -0.9904812214919188
    },
    {
      "symbol": "^ndx",
      "name": "NASDAQ 100",
      "price": 25734.81,
      "change": -385.03999999999724,
      "changePercent": -1.4741279142108292
    },
    {
      "symbol": "^hsi",
      "name": "Hang Seng",
      "price": 26000.41,
      "change": -282.27999999999884,
      "changePercent": -1.0740148744287545
    },
    {
      "symbol": "^shc",
      "name": "Shanghai Comp.",
      "price": 3952.2689,
      "change": -34.63189999999986,
      "changePercent": -0.8686421292448475
    }
  ]
}