{
  "updatedAt": "03-02-2026, 11:38:36 pm",
  "items": [
    {
      "symbol": "^spx",
      "name": "S&P 500",
      "price": 6906.43,
      "change": -70.00999999999931,
      "changePercent": -1.0035204201569756
    },
    {
      "symbol": "^ndx",
      "name": "NASDAQ 100",
      "price": 25311.984,
      "change": -426.6260000000002,
      "changePercent": -1.657533176811025
    },
    {
      "symbol": "^hsi",
      "name": "Hang Seng",
      "price": 26834.77,
      "change": 59.20000000000073,
      "changePercent": 0.22109706721463157
    },
    {
      "symbol": "^shc",
      "name": "Shanghai Comp.",
      "price": 4067.7379,
      "change": 51.99150000000009,
      "changePercent": 1.2946908201175276
    }
  ]
}