{
  "updatedAt": "2025-08-29T20:08:54+05:30",
  "items": [
    {
      "symbol": "^spx",
      "name": "S&P 500",
      "price": 6461.35,
      "change": -40.50999999999931,
      "changePercent": -0.6230524803671459,
      "marketState": "DAILY"
    },
    {
      "symbol": "^ndx",
      "name": "NASDAQ 100",
      "price": 23458.887,
      "change": -244.56300000000192,
      "changePercent": -1.0317611993190945,
      "marketState": "DAILY"
    },
    {
      "symbol": "^kospi",
      "name": "KOSPI (Korea)",
      "price": 3188.06,
      "change": -13.320000000000164,
      "changePercent": -0.4160705695668794,
      "marketState": "DAILY"
    },
    {
      "symbol": "^nkx",
      "name": "Nikkei 225",
      "price": 42718.47,
      "change": -110.31999999999971,
      "changePercent": -0.25758374215101504,
      "marketState": "DAILY"
    },
    {
      "symbol": "^hsi",
      "name": "Hang Seng",
      "price": 25077.62,
      "change": 78.79999999999927,
      "changePercent": 0.3152148781422454,
      "marketState": "DAILY"
    },
    {
      "symbol": "^dax",
      "name": "DAX (Germany)",
      "price": 23949.79,
      "change": -90.12999999999738,
      "changePercent": -0.37491805297187925,
      "marketState": "DAILY"
    }
  ]
}