{
  "updatedAt": "09-10-2025, 02:53:28 pm",
  "items": [
    {
      "symbol": "^spx",
      "name": "S&P 500",
      "price": 6753.72,
      "change": 39.13000000000011,
      "changePercent": 0.582760823817986
    },
    {
      "symbol": "^ndx",
      "name": "NASDAQ 100",
      "price": 25136.62,
      "change": 296.3899999999994,
      "changePercent": 1.1931854093138405
    },
    {
      "symbol": "^hsi",
      "name": "Hang Seng",
      "price": 26752.59,
      "change": -76.86999999999898,
      "changePercent": -0.28651340727692237
    },
    {
      "symbol": "^shc",
      "name": "Shanghai Comp.",
      "price": 3933.9724,
      "change": 51.195000000000164,
      "changePercent": 1.3185149372714533
    }
  ]
}