{
  "updatedAt": "20-10-2025, 08:54:37 pm",
  "items": [
    {
      "symbol": "^spx",
      "name": "S&P 500",
      "price": 6730.8,
      "change": 66.78999999999996,
      "changePercent": 1.0022493963844585
    },
    {
      "symbol": "^ndx",
      "name": "NASDAQ 100",
      "price": 25150.904,
      "change": 332.9539999999979,
      "changePercent": 1.3415854250653172
    },
    {
      "symbol": "^hsi",
      "name": "Hang Seng",
      "price": 25858.83,
      "change": 611.7300000000032,
      "changePercent": 2.422971351165097
    },
    {
      "symbol": "^shc",
      "name": "Shanghai Comp.",
      "price": 3863.8926,
      "change": 24.137300000000323,
      "changePercent": 0.6286155787062869
    }
  ]
}